MANIFEST.in
README.rst
setup.py
aliyun_python_sdk_arms_test.egg-info/PKG-INFO
aliyun_python_sdk_arms_test.egg-info/SOURCES.txt
aliyun_python_sdk_arms_test.egg-info/dependency_links.txt
aliyun_python_sdk_arms_test.egg-info/requires.txt
aliyun_python_sdk_arms_test.egg-info/top_level.txt
aliyunsdkarms/__init__.py
aliyunsdkarms/request/__init__.py
aliyunsdkarms/request/v20160804/ArmsQueryDataSetRequest.py
aliyunsdkarms/request/v20160804/__init__.py
aliyunsdkarms/request/v20181219/ARMSQueryDataSetRequest.py
aliyunsdkarms/request/v20181219/CreateAppRequest.py
aliyunsdkarms/request/v20181219/DeleteAppRequest.py
aliyunsdkarms/request/v20181219/MetricQueryRequest.py
aliyunsdkarms/request/v20181219/__init__.py